echemdb/__init__.py
echemdb/database.py
echemdb/descriptor.py
echemdb/entry.py
echemdb/local.py
echemdb/remote.py
echemdb/cv/__init__.py
echemdb/cv/cv_database.py
echemdb/cv/cv_entry.py
echemdb-0.6.0.dist-info/LICENSE
echemdb-0.6.0.dist-info/METADATA
echemdb-0.6.0.dist-info/WHEEL
echemdb-0.6.0.dist-info/top_level.txt
echemdb-0.6.0.dist-info/RECORD
