Metadata-Version: 2.1
Name: echemdb
Version: 0.6.0
Summary: a Python library to work with the echemdb repository
License: GPL 3.0+
Requires-Python: >=3.9
License-File: LICENSE
Requires-Dist: astropy (<6,>=5)
Requires-Dist: filelock (<4,>=3)
Requires-Dist: frictionless (<6,>=5.10.1)
Requires-Dist: matplotlib (<4,>=3.5.0)
Requires-Dist: pandas (<2,>=1)
Requires-Dist: plotly (<6,>=5)
Requires-Dist: pybtex (<0.25,>=0.24)
Requires-Dist: svgdigitizer (<0.11.0,>=0.10.0)
